[
	{
		"predicate": {
			"item": "endreborn:wolframium_sword"
		},
		"item": "tetra:modular_sword",
		"modules": {
			"sword/blade": ["sword/basic_blade", "basic_blade/tungsten"],
			"sword/hilt": ["sword/basic_hilt", "basic_hilt/stick"],
			"sword/pommel": ["sword/decorative_pommel", "decorative_pommel/tungsten"],
			"sword/guard": ["sword/makeshift_guard", "makeshift_guard/tungsten"]
		}
	},
	{
		"predicate": {
			"item": "endreborn:endorium_sword"
		},
		"item": "tetra:modular_sword",
		"modules": {
			"sword/blade": ["sword/basic_blade", "basic_blade/endorium"],
			"sword/hilt": ["sword/basic_hilt", "basic_hilt/stick"],
			"sword/pommel": ["sword/decorative_pommel", "decorative_pommel/endorium"],
			"sword/guard": ["sword/makeshift_guard", "makeshift_guard/endorium"]
		}
	},
	{
		"predicate": {
			"item": "endreborn:end_stone_sword"
		},
		"item": "tetra:modular_sword",
		"modules": {
			"sword/blade": ["sword/basic_blade", "basic_blade/end_stone"],
			"sword/hilt": ["sword/basic_hilt", "basic_hilt/stick"],
			"sword/pommel": ["sword/decorative_pommel", "decorative_pommel/end_stone"],
			"sword/guard": ["sword/makeshift_guard", "makeshift_guard/end_stone"]
		}
	}
]